dishka_jobify/__init__.py
dishka_jobify/_consts.py
dishka_jobify/_getters.py
dishka_jobify/_injectors.py
dishka_jobify/_middlewares.py
dishka_jobify/_version.py
dishka_jobify/jobify.py
dishka_jobify/py.typed
dishka_jobify-0.0.1.dist-info/METADATA
dishka_jobify-0.0.1.dist-info/WHEEL
dishka_jobify-0.0.1.dist-info/licenses/LICENSE
dishka_jobify-0.0.1.dist-info/RECORD
