Metadata-Version: 2.4
Name: dishka-jobify
Version: 0.0.1
Summary: Integration package for Dishka DI and Jobify framework
Project-URL: Source, https://github.com/C3EQUALZz/dishka-jobify
Project-URL: Homepage, https://github.com/C3EQUALZz/dishka-jobify
Project-URL: Tracker, https://github.com/C3EQUALZz/dishka-jobify/issues
Author-email: Danil Kovalev <dan.kovalev2013@gmail.com>
License-Expression: Apache-2.0
License-File: LICENSE
Classifier: Intended Audience :: Developers
Classifier: License :: OSI Approved :: Apache Software License
Classifier: Operating System :: OS Independent
Classifier: Programming Language :: Python :: 3.10
Classifier: Programming Language :: Python :: 3.11
Classifier: Programming Language :: Python :: 3.12
Classifier: Programming Language :: Python :: 3.13
Classifier: Programming Language :: Python :: 3.14
Classifier: Topic :: Software Development :: Libraries
Classifier: Typing :: Typed
Requires-Python: >=3.10
Requires-Dist: dishka<2,>=1.7
Requires-Dist: jobify>=0.3.3
